agora_gps/__init__.py
agora_gps/curl_wrapper.py
agora_gps/gps.py
agora_gps/version.py
agora_gps-3.0.2.dist-info/licenses/LICENSE
agora_gps-3.0.2.dist-info/WHEEL
agora_gps-3.0.2.dist-info/METADATA
agora_gps-3.0.2.dist-info/RECORD
